common/__init__.py
common/appointment.py
common/config_loader.py
common/constants.py
common/cryptographer.py
common/db_manager.py
common/errors.py
common/exceptions.py
common/receipts.py
common/tools.py
teos_common-0.1.1.dist-info/METADATA
teos_common-0.1.1.dist-info/WHEEL
teos_common-0.1.1.dist-info/top_level.txt
teos_common-0.1.1.dist-info/RECORD
